recognizers_number_with_unit/__init__.py
recognizers_number_with_unit/number_with_unit/__init__.py
recognizers_number_with_unit/number_with_unit/constants.py
recognizers_number_with_unit/number_with_unit/extractors.py
recognizers_number_with_unit/number_with_unit/models.py
recognizers_number_with_unit/number_with_unit/number_with_unit_recognizer.py
recognizers_number_with_unit/number_with_unit/parsers.py
recognizers_number_with_unit/number_with_unit/utilities.py
recognizers_number_with_unit/number_with_unit/chinese/__init__.py
recognizers_number_with_unit/number_with_unit/chinese/extractors.py
recognizers_number_with_unit/number_with_unit/chinese/parsers.py
recognizers_number_with_unit/number_with_unit/english/__init__.py
recognizers_number_with_unit/number_with_unit/english/extractors.py
recognizers_number_with_unit/number_with_unit/english/parsers.py
recognizers_number_with_unit/number_with_unit/french/__init__.py
recognizers_number_with_unit/number_with_unit/french/extractors.py
recognizers_number_with_unit/number_with_unit/french/parsers.py
recognizers_number_with_unit/number_with_unit/portuguese/__init__.py
recognizers_number_with_unit/number_with_unit/portuguese/extractors.py
recognizers_number_with_unit/number_with_unit/portuguese/parsers.py
recognizers_number_with_unit/number_with_unit/spanish/__init__.py
recognizers_number_with_unit/number_with_unit/spanish/extractors.py
recognizers_number_with_unit/number_with_unit/spanish/parsers.py
recognizers_number_with_unit/resources/__init__.py
recognizers_number_with_unit/resources/base_currency.py
recognizers_number_with_unit/resources/base_numbers.py
recognizers_number_with_unit/resources/base_units.py
recognizers_number_with_unit/resources/chinese_numeric_with_unit.py
recognizers_number_with_unit/resources/english_numeric_with_unit.py
recognizers_number_with_unit/resources/french_numeric_with_unit.py
recognizers_number_with_unit/resources/portuguese_numeric_with_unit.py
recognizers_number_with_unit-1.0.0a1.dist-info/METADATA
recognizers_number_with_unit-1.0.0a1.dist-info/WHEEL
recognizers_number_with_unit-1.0.0a1.dist-info/top_level.txt
recognizers_number_with_unit-1.0.0a1.dist-info/RECORD
